webrtc_streaming/__init__.py
webrtc_streaming/streamer.py
webrtc_streaming-0.1.8.dist-info/AUTHORS.rst
webrtc_streaming-0.1.8.dist-info/LICENSE
webrtc_streaming-0.1.8.dist-info/METADATA
webrtc_streaming-0.1.8.dist-info/WHEEL
webrtc_streaming-0.1.8.dist-info/top_level.txt
webrtc_streaming-0.1.8.dist-info/RECORD
