Metadata-Version: 2.1
Name: webrtc-streaming
Version: 0.1.8
Summary: Ready to use WebRTC Streaming
Home-page: https://github.com/Utring/webrtc_streaming
Author: Carlos Tovar
Author-email: cartovarc@gmail.com
License: BSD license
Keywords: webrtc_streaming
Platform: UNKNOWN
Classifier: Development Status :: 2 - Pre-Alpha
Classifier: Intended Audience :: Developers
Classifier: License :: OSI Approved :: BSD License
Classifier: Natural Language :: English
Classifier: Programming Language :: Python :: 3.8
Requires-Python: >=3.5
Requires-Dist: aiortc (==1.0.0)
Requires-Dist: aiohttp (==3.7.3)
Requires-Dist: python-socketio (==4.6.0)
Requires-Dist: python-engineio (==3.14.2)
